Component2/alu.sv
module alu #(
    parameter           DATA_WIDTH = 32
) (
    input logic                     ALUctrl,        // what is this used for?
    input logic [DATA_WIDTH-1:0]    ALUop1,         // 1st data to add
    input logic [DATA_WIDTH-1:0]    ALUop2,         // 2nd data to add

    output logic                    EQ,             // 1 if both input are the same
    output logic [DATA_WIDTH-1:0]   ALUout          // result of operation
);

always_latch begin
    if(ALUctrl) begin
        ALUout = ALUop1 + ALUop2;
        if( (ALUop1 - ALUop2) == 'b0 ) EQ = 'b1;
    end
end

endmodule

Component2/mux2.sv
module mux2 #(
    parameter       DATA_WIDTH = 32
) (
    input logic                     select,
    input logic [DATA_WIDTH-1:0]    channel0,
    input logic [DATA_WIDTH-1:0]    channel1,

    output logic [DATA_WIDTH-1:0]   muxRes
);

always_comb 
    assign muxRes = select ? channel1 : channel0;

endmodule

Component2/regFile.sv
module regFile #(
    parameter       ADD_WIDTH = 5,
                    DATA_WIDTH = 32
)(
    input logic                     clk,

    input logic [ADD_WIDTH-1:0]    AD1,     //to extenal in top level | register 1
    input logic [ADD_WIDTH-1:0]    AD2,     //to extenal | register 2
    input logic [ADD_WIDTH-1:0]    AD3,     //to extenal | to store results
    input logic [DATA_WIDTH-1:0]    WD3,    //to extenal | write to register
    input logic                     WE3,    //to extenal | write enable

    output logic [DATA_WIDTH-1:0]   RD1,    //internal in top level
    output logic [DATA_WIDTH-1:0]   RD2,    //internal
    output logic [DATA_WIDTH-1:0]   a0      //internal | what is a0
);

// create 32 registers
// initialise all to zero
// this number of location is 2**ADD_WIDTH-1 but this is too large!!
// so we use only what we need.
logic [DATA_WIDTH-1:0] register [31:0];

always_ff @ (posedge clk) begin
    if(AD1 != 'b00000) RD1 <= register[AD1];            //output register at RD1
    if(AD2 != 'b00000) RD2 <= register[AD2];            //output register at RD2
    if(AD3 != 'b00000 & WE3) register[AD3] <= WD3;      //store result from WE3
    a0 <= register[10];
end

endmodule

Component2/top.sv
module top #(
    parameter       ADD_WIDTH  = 5,
                    IMM_WIDTH  = 12,
                    DATA_WIDTH = 12
) (
    input logic                     clk,
    input logic [ADD_WIDTH-1:0]     rs1,
    input logic [ADD_WIDTH-1:0]     rs2,
    input logic [ADD_WIDTH-1:0]     rd,
    input logic                     RegWrite,
    input logic [IMM_WIDTH-1:0]     ImmOp,
    input logic                     ALUsrc,
    input logic                     ALUctrl,

    output logic [DATA_WIDTH-1:0]   a0,
    output logic                    EQ
);

logic [DATA_WIDTH-1:0]      regOp2;
logic [DATA_WIDTH-1:0]      ALUout;
logic [DATA_WIDTH-1:0]      ALUop1;
logic [DATA_WIDTH-1:0]      ALUop2;

regFile regFile(
    .clk        (clk),
    .AD1        (rs1),
    .AD2        (rs2),
    .AD3        (rd),
    .WD3        (ALUout),                // internal use
    .WE3        (RegWrite),
    .RD1        (ALUop1),                // internal use
    .RD2        (regOp2),                // internal use
    .a0         (a0)
);

mux2 mux(
    .select     (ALUsrc),
    .channel0   (regOp2),
    .channel1   (ImmOp),
    .muxRes     (ALUop2)
);

alu alu(
    .ALUctrl    (ALUctrl),
    .ALUop1     (ALUop1),
    .ALUop2     (ALUop2),
    .EQ         (EQ),
    .ALUout     (ALUout)
);

endmodule

Component2/top.vcd
$version Generated by VerilatedVcd $end
$date Mon Nov 20 17:39:09 2023 $end
$timescale 1ps $end

 $scope module TOP $end
  $var wire  1 L ALUctrl $end
  $var wire  1 K ALUsrc $end
  $var wire  1 N EQ $end
  $var wire 32 J ImmOp [31:0] $end
  $var wire  1 I RegWrite $end
  $var wire 32 M a0 [31:0] $end
  $var wire  1 E clk $end
  $var wire  5 H rd [4:0] $end
  $var wire  5 F rs1 [4:0] $end
  $var wire  5 G rs2 [4:0] $end
  $scope module top $end
   $var wire 32 Q ADD_WIDTH [31:0] $end
   $var wire  1 L ALUctrl $end
   $var wire 32 $ ALUop1 [31:0] $end
   $var wire 32 P ALUop2 [31:0] $end
   $var wire 32 O ALUout [31:0] $end
   $var wire  1 K ALUsrc $end
   $var wire 32 R DATA_WIDTH [31:0] $end
   $var wire  1 N EQ $end
   $var wire 32 R IMM_WIDTH [31:0] $end
   $var wire 32 J ImmOp [31:0] $end
   $var wire  1 I RegWrite $end
   $var wire 32 M a0 [31:0] $end
   $var wire  1 E clk $end
   $var wire  5 H rd [4:0] $end
   $var wire 32 # regOp2 [31:0] $end
   $var wire  5 F rs1 [4:0] $end
   $var wire  5 G rs2 [4:0] $end
   $scope module alu $end
    $var wire  1 L ALUctrl $end
    $var wire 32 $ ALUop1 [31:0] $end
    $var wire 32 P ALUop2 [31:0] $end
    $var wire 32 O ALUout [31:0] $end
    $var wire 32 R DATA_WIDTH [31:0] $end
    $var wire  1 N EQ $end
   $upscope $end
   $scope module mux $end
    $var wire 32 R DATA_WIDTH [31:0] $end
    $var wire 32 # channel0 [31:0] $end
    $var wire 32 J channel1 [31:0] $end
    $var wire 32 P muxRes [31:0] $end
    $var wire  1 K select $end
   $upscope $end
   $scope module regFile $end
    $var wire  5 F AD1 [4:0] $end
    $var wire  5 G AD2 [4:0] $end
    $var wire  5 H AD3 [4:0] $end
    $var wire 32 Q ADD_WIDTH [31:0] $end
    $var wire 32 R DATA_WIDTH [31:0] $end
    $var wire 32 $ RD1 [31:0] $end
    $var wire 32 # RD2 [31:0] $end
    $var wire 32 O WD3 [31:0] $end
    $var wire  1 I WE3 $end
    $var wire 32 M a0 [31:0] $end
    $var wire  1 E clk $end
    $var wire 32 % register[0] [31:0] $end
    $var wire 32 / register[10] [31:0] $end
    $var wire 32 0 register[11] [31:0] $end
    $var wire 32 1 register[12] [31:0] $end
    $var wire 32 2 register[13] [31:0] $end
    $var wire 32 3 register[14] [31:0] $end
    $var wire 32 4 register[15] [31:0] $end
    $var wire 32 5 register[16] [31:0] $end
    $var wire 32 6 register[17] [31:0] $end
    $var wire 32 7 register[18] [31:0] $end
    $var wire 32 8 register[19] [31:0] $end
    $var wire 32 & register[1] [31:0] $end
    $var wire 32 9 register[20] [31:0] $end
    $var wire 32 : register[21] [31:0] $end
    $var wire 32 ; register[22] [31:0] $end
    $var wire 32 < register[23] [31:0] $end
    $var wire 32 = register[24] [31:0] $end
    $var wire 32 > register[25] [31:0] $end
    $var wire 32 ? register[26] [31:0] $end
    $var wire 32 @ register[27] [31:0] $end
    $var wire 32 A register[28] [31:0] $end
    $var wire 32 B register[29] [31:0] $end
    $var wire 32 ' register[2] [31:0] $end
    $var wire 32 C register[30] [31:0] $end
    $var wire 32 D register[31] [31:0] $end
    $var wire 32 ( register[3] [31:0] $end
    $var wire 32 ) register[4] [31:0] $end
    $var wire 32 * register[5] [31:0] $end
    $var wire 32 + register[6] [31:0] $end
    $var wire 32 , register[7] [31:0] $end
    $var wire 32 - register[8] [31:0] $end
    $var wire 32 . register[9] [31:0] $end
   $upscope $end
  $upscope $end
 $upscope $end
$enddefinitions $end


#0
b00000000000000000000000000000000 #
b00000000000000000000000000000000 $
b00000000000000000000000000000000 %
b00000000000000000000000000000000 &
b00000000000000000000000000000000 '
b00000000000000000000000000000000 (
b00000000000000000000000000000000 )
b00000000000000000000000000000000 *
b00000000000000000000000000000000 +
b00000000000000000000000000000000 ,
b00000000000000000000000000000000 -
b00000000000000000000000000000000 .
b00000000000000000000000000000000 /
b00000000000000000000000000000000 0
b00000000000000000000000000000000 1
b00000000000000000000000000000000 2
b00000000000000000000000000000000 3
b00000000000000000000000000000000 4
b00000000000000000000000000000000 5
b00000000000000000000000000000000 6
b00000000000000000000000000000000 7
b00000000000000000000000000000000 8
b00000000000000000000000000000000 9
b00000000000000000000000000000000 :
b00000000000000000000000000000000 ;
b00000000000000000000000000000000 <
b00000000000000000000000000000000 =
b00000000000000000000000000000000 >
b00000000000000000000000000000000 ?
b00000000000000000000000000000000 @
b00000000000000000000000000000000 A
b00000000000000000000000000000000 B
b00000000000000000000000000000000 C
b00000000000000000000000000000000 D
1E
b00000 F
b00000 G
b01010 H
1I
b00000000000000000000000000000000 J
1K
1L
b00000000000000000000000000000000 M
0N
b00000000000000000000000000000000 O
b00000000000000000000000000000000 P
b00000000000000000000000000000101 Q
b00000000000000000000000000100000 R
#1
0E
1N
#2
1E
b01010 F
b01011 H
b00000000000000000000000000000001 J
#3
0E
b00000000000000000000000000000001 O
b00000000000000000000000000000001 P
#4
b00000000000000000000000000000001 0
1E
b01011 F
b01010 H
b00000000000000000000000000000000 J
#5
0E
b00000000000000000000000000000000 O
b00000000000000000000000000000000 P
#6
b00000000000000000000000000000001 $
1E
b01010 F
b01011 H
b00000000000000000000000000000001 J
b00000000000000000000000000000001 O
#7
0E
b00000000000000000000000000000010 O
b00000000000000000000000000000001 P
#8
b00000000000000000000000000000000 $
b00000000000000000000000000000010 0
1E
b01011 F
b01010 H
b00000000000000000000000000000000 J
b00000000000000000000000000000001 O
#9
0E
b00000000000000000000000000000000 O
b00000000000000000000000000000000 P
#10
b00000000000000000000000000000010 $
1E
b01010 F
b01011 H
b00000000000000000000000000000001 J
b00000000000000000000000000000010 O
#11
0E
b00000000000000000000000000000011 O
b00000000000000000000000000000001 P
#12
b00000000000000000000000000000000 $
b00000000000000000000000000000011 0
1E
b01011 F
b01010 H
b00000000000000000000000000000000 J
b00000000000000000000000000000001 O
#13
0E
b00000000000000000000000000000000 O
b00000000000000000000000000000000 P
#14
b00000000000000000000000000000011 $
1E
b01010 F
b01011 H
b00000000000000000000000000000001 J
b00000000000000000000000000000011 O
#15
0E
b00000000000000000000000000000100 O
b00000000000000000000000000000001 P
#16
b00000000000000000000000000000000 $
b00000000000000000000000000000100 0
1E
b01011 F
b01010 H
b00000000000000000000000000000000 J
b00000000000000000000000000000001 O
#17
0E
b00000000000000000000000000000000 O
b00000000000000000000000000000000 P
#18
b00000000000000000000000000000100 $
1E
b01010 F
b01011 H
b00000000000000000000000000000001 J
b00000000000000000000000000000100 O
#19
0E
b00000000000000000000000000000101 O
b00000000000000000000000000000001 P
#20
b00000000000000000000000000000000 $
b00000000000000000000000000000101 0
1E
b01011 F
b01010 H
b00000000000000000000000000000000 J
b00000000000000000000000000000001 O
#21
0E
b00000000000000000000000000000000 O
b00000000000000000000000000000000 P
#22
b00000000000000000000000000000101 $
1E
b01010 F
b01011 H
b00000000000000000000000000000001 J
b00000000000000000000000000000101 O
#23
0E
b00000000000000000000000000000110 O
b00000000000000000000000000000001 P
#24
b00000000000000000000000000000000 $
b00000000000000000000000000000110 0
1E
b01011 F
b01010 H
b00000000000000000000000000000000 J
b00000000000000000000000000000001 O
#25
0E
b00000000000000000000000000000000 O
b00000000000000000000000000000000 P
#26
b00000000000000000000000000000110 $
1E
b01010 F
b01011 H
b00000000000000000000000000000001 J
b00000000000000000000000000000110 O
#27
0E
b00000000000000000000000000000111 O
b00000000000000000000000000000001 P
#28
b00000000000000000000000000000000 $
b00000000000000000000000000000111 0
1E
b01011 F
b01010 H
b00000000000000000000000000000000 J
b00000000000000000000000000000001 O
#29
0E
b00000000000000000000000000000000 O
b00000000000000000000000000000000 P
#30
b00000000000000000000000000000111 $
1E
b01010 F
b01011 H
b00000000000000000000000000000001 J
b00000000000000000000000000000111 O
#31
0E
b00000000000000000000000000001000 O
b00000000000000000000000000000001 P
#32
b00000000000000000000000000000000 $
b00000000000000000000000000001000 0
1E
b01011 F
b01010 H
b00000000000000000000000000000000 J
b00000000000000000000000000000001 O
#33
0E
b00000000000000000000000000000000 O
b00000000000000000000000000000000 P
#34
b00000000000000000000000000001000 $
1E
b01010 F
b01011 H
b00000000000000000000000000000001 J
b00000000000000000000000000001000 O
#35
0E
b00000000000000000000000000001001 O
b00000000000000000000000000000001 P
#36
b00000000000000000000000000000000 $
b00000000000000000000000000001001 0
1E
b01011 F
b01010 H
b00000000000000000000000000000000 J
b00000000000000000000000000000001 O
#37
0E
b00000000000000000000000000000000 O
b00000000000000000000000000000000 P
#38
b00000000000000000000000000001001 $
1E
b01010 F
b01011 H
b00000000000000000000000000000001 J
b00000000000000000000000000001001 O
#39
0E
b00000000000000000000000000001010 O
b00000000000000000000000000000001 P
#40
b00000000000000000000000000000000 $
b00000000000000000000000000001010 0
1E
b01011 F
b01010 H
b00000000000000000000000000000000 J
b00000000000000000000000000000001 O
#41
0E
b00000000000000000000000000000000 O
b00000000000000000000000000000000 P
#42
b00000000000000000000000000001010 $
1E
b01010 F
b01011 H
b00000000000000000000000000000001 J
b00000000000000000000000000001010 O
#43
0E
b00000000000000000000000000001011 O
b00000000000000000000000000000001 P
#44
b00000000000000000000000000000000 $
b00000000000000000000000000001011 0
1E
b01011 F
b01010 H
b00000000000000000000000000000000 J
b00000000000000000000000000000001 O
#45
0E
b00000000000000000000000000000000 O
b00000000000000000000000000000000 P
#46
b00000000000000000000000000001011 $
1E
b01010 F
b01011 H
b00000000000000000000000000000001 J
b00000000000000000000000000001011 O
#47
0E
b00000000000000000000000000001100 O
b00000000000000000000000000000001 P
#48
b00000000000000000000000000000000 $
b00000000000000000000000000001100 0
1E
b01011 F
b01010 H
b00000000000000000000000000000000 J
b00000000000000000000000000000001 O
#49
0E
b00000000000000000000000000000000 O
b00000000000000000000000000000000 P
#50
b00000000000000000000000000001100 $
1E
b01010 F
b01011 H
b00000000000000000000000000000001 J
b00000000000000000000000000001100 O
#51
0E
b00000000000000000000000000001101 O
b00000000000000000000000000000001 P
#52
b00000000000000000000000000000000 $
b00000000000000000000000000001101 0
1E
b01011 F
b01010 H
b00000000000000000000000000000000 J
b00000000000000000000000000000001 O
#53
0E
b00000000000000000000000000000000 O
b00000000000000000000000000000000 P
#54
b00000000000000000000000000001101 $
1E
b01010 F
b01011 H
b00000000000000000000000000000001 J
b00000000000000000000000000001101 O
#55
0E
b00000000000000000000000000001110 O
b00000000000000000000000000000001 P
#56
b00000000000000000000000000000000 $
b00000000000000000000000000001110 0
1E
b01011 F
b01010 H
b00000000000000000000000000000000 J
b00000000000000000000000000000001 O
#57
0E
b00000000000000000000000000000000 O
b00000000000000000000000000000000 P
#58
b00000000000000000000000000001110 $
1E
b01010 F
b01011 H
b00000000000000000000000000000001 J
b00000000000000000000000000001110 O
#59
0E
b00000000000000000000000000001111 O
b00000000000000000000000000000001 P
#60
b00000000000000000000000000000000 $
b00000000000000000000000000001111 0
1E
b01011 F
b01010 H
b00000000000000000000000000000000 J
b00000000000000000000000000000001 O
#61
0E
b00000000000000000000000000000000 O
b00000000000000000000000000000000 P
#62
b00000000000000000000000000001111 $
1E
b01010 F
b01011 H
b00000000000000000000000000000001 J
b00000000000000000000000000001111 O
#63
0E
b00000000000000000000000000010000 O
b00000000000000000000000000000001 P
#64
b00000000000000000000000000000000 $
b00000000000000000000000000010000 0
1E
b01011 F
b01010 H
b00000000000000000000000000000000 J
b00000000000000000000000000000001 O
#65
0E
b00000000000000000000000000000000 O
b00000000000000000000000000000000 P
#66
b00000000000000000000000000010000 $
1E
b01010 F
b01011 H
b00000000000000000000000000000001 J
b00000000000000000000000000010000 O
#67
0E
b00000000000000000000000000010001 O
b00000000000000000000000000000001 P
#68
b00000000000000000000000000000000 $
b00000000000000000000000000010001 0
1E
b01011 F
b01010 H
b00000000000000000000000000000000 J
b00000000000000000000000000000001 O
#69
0E
b00000000000000000000000000000000 O
b00000000000000000000000000000000 P
#70
b00000000000000000000000000010001 $
1E
b01010 F
b01011 H
b00000000000000000000000000000001 J
b00000000000000000000000000010001 O
#71
0E
b00000000000000000000000000010010 O
b00000000000000000000000000000001 P
#72
b00000000000000000000000000000000 $
b00000000000000000000000000010010 0
1E
b01011 F
b01010 H
b00000000000000000000000000000000 J
b00000000000000000000000000000001 O
#73
0E
b00000000000000000000000000000000 O
b00000000000000000000000000000000 P
#74
b00000000000000000000000000010010 $
1E
b01010 F
b01011 H
b00000000000000000000000000000001 J
b00000000000000000000000000010010 O
#75
0E
b00000000000000000000000000010011 O
b00000000000000000000000000000001 P
#76
b00000000000000000000000000000000 $
b00000000000000000000000000010011 0
1E
b01011 F
b01010 H
b00000000000000000000000000000000 J
b00000000000000000000000000000001 O
#77
0E
b00000000000000000000000000000000 O
b00000000000000000000000000000000 P
#78
b00000000000000000000000000010011 $
1E
b01010 F
b01011 H
b00000000000000000000000000000001 J
b00000000000000000000000000010011 O
#79
0E
b00000000000000000000000000010100 O
b00000000000000000000000000000001 P
#80
b00000000000000000000000000000000 $
b00000000000000000000000000010100 0
1E
b01011 F
b01010 H
b00000000000000000000000000000000 J
b00000000000000000000000000000001 O
#81
0E
b00000000000000000000000000000000 O
b00000000000000000000000000000000 P
#82
b00000000000000000000000000010100 $
1E
b01010 F
b01011 H
b00000000000000000000000000000001 J
b00000000000000000000000000010100 O
#83
0E
b00000000000000000000000000010101 O
b00000000000000000000000000000001 P
#84
b00000000000000000000000000000000 $
b00000000000000000000000000010101 0
1E
b01011 F
b01010 H
b00000000000000000000000000000000 J
b00000000000000000000000000000001 O
#85
0E
b00000000000000000000000000000000 O
b00000000000000000000000000000000 P
#86
b00000000000000000000000000010101 $
1E
b01010 F
b01011 H
b00000000000000000000000000000001 J
b00000000000000000000000000010101 O
#87
0E
b00000000000000000000000000010110 O
b00000000000000000000000000000001 P
#88
b00000000000000000000000000000000 $
b00000000000000000000000000010110 0
1E
b01011 F
b01010 H
b00000000000000000000000000000000 J
b00000000000000000000000000000001 O
#89
0E
b00000000000000000000000000000000 O
b00000000000000000000000000000000 P
#90
b00000000000000000000000000010110 $
1E
b01010 F
b01011 H
b00000000000000000000000000000001 J
b00000000000000000000000000010110 O
#91
0E
b00000000000000000000000000010111 O
b00000000000000000000000000000001 P
#92
b00000000000000000000000000000000 $
b00000000000000000000000000010111 0
1E
b01011 F
b01010 H
b00000000000000000000000000000000 J
b00000000000000000000000000000001 O
#93
0E
b00000000000000000000000000000000 O
b00000000000000000000000000000000 P
#94
b00000000000000000000000000010111 $
1E
b01010 F
b01011 H
b00000000000000000000000000000001 J
b00000000000000000000000000010111 O
#95
0E
b00000000000000000000000000011000 O
b00000000000000000000000000000001 P
#96
b00000000000000000000000000000000 $
b00000000000000000000000000011000 0
1E
b01011 F
b01010 H
b00000000000000000000000000000000 J
b00000000000000000000000000000001 O
#97
0E
b00000000000000000000000000000000 O
b00000000000000000000000000000000 P
#98
b00000000000000000000000000011000 $
1E
b01010 F
b01011 H
b00000000000000000000000000000001 J
b00000000000000000000000000011000 O
#99
0E
b00000000000000000000000000011001 O
b00000000000000000000000000000001 P
