Component1/ProgramCounter.sv
module ProgramCounter #(            //works as an adder
    parameter DATA_WIDTH = 32
)(
    input logic                         clk,
    input logic                         rst,         
    input logic                         PCsrc, 
    input logic [DATA_WIDTH-1:0]        ImmOp, 
    input logic [DATA_WIDTH-1:0]        PC,
    output logic [DATA_WIDTH-1:0]       next_PC    
);


always_ff @(posedge clk, posedge rst, posedge PCsrc) begin     //asynchronous
    if (rst)            next_PC <= 32'b0;
    if (PCsrc)          next_PC <= PC + ImmOp; 
    else                next_PC <= PC + 32'b0100;  
end

endmodule

Component1/PCReg.sv
module PCReg #(         //topfile
    parameter       DATA_WIDTH = 32
) (
    input logic                     clk,               
    input logic                     rst,
    input logic [DATA_WIDTH-1:0]    PCsrc,  
    input logic [DATA_WIDTH-1:0]    ImmOp,
    output logic [DATA_WIDTH-1:0]   PC   
);
    logic [DATA_WIDTH-1:0]   next_PC;


ProgramCounter counter (
    .clk (clk),
    .rst (rst),
    .PCsrc (PCsrc),
    .ImmOp (ImmOp),
    .PC (PC),
    .next_PC (PC)
);

endmodule

Component1/PCReg.vcd
$version Generated by VerilatedVcd $end
$timescale 1ps $end

 $scope module TOP $end
  $var wire 32 & ImmOp [31:0] $end
  $var wire 32 ' PC [31:0] $end
  $var wire 32 % PCsrc [31:0] $end
  $var wire  1 # clk $end
  $var wire  1 $ rst $end
  $scope module PCReg $end
   $var wire 32 ) DATA_WIDTH [31:0] $end
   $var wire 32 & ImmOp [31:0] $end
   $var wire 32 ' PC [31:0] $end
   $var wire 32 % PCsrc [31:0] $end
   $var wire  1 # clk $end
   $var wire 32 * next_PC [31:0] $end
   $var wire  1 $ rst $end
   $scope module counter $end
    $var wire 32 ) DATA_WIDTH [31:0] $end
    $var wire 32 & ImmOp [31:0] $end
    $var wire 32 ' PC [31:0] $end
    $var wire  1 ( PCsrc $end
    $var wire  1 # clk $end
    $var wire 32 ' next_PC [31:0] $end
    $var wire  1 $ rst $end
   $upscope $end
  $upscope $end
 $upscope $end
$enddefinitions $end


#0
1#
0$
b00000000000000000000000000000000 %
b00000000000000000000000000000000 &
b00000000000000000000000000000000 '
0(
b00000000000000000000000000100000 )
b00000000000000000000000000000000 *
#1
0#
#2
1#
b00000000000000000000000000000100 '
#3
0#
#4
1#
b00000000000000000000000000001000 '
#5
0#
#6
1#
b00000000000000000000000000001100 '
#7
0#
#8
1#
b00000000000000000000000000010000 '
#9
0#
#10
1#
b00000000000000000000000000010100 '
#11
0#
#12
1#
b00000000000000000000000000011000 '
#13
0#
#14
1#
b00000000000000000000000000011100 '
#15
0#
#16
1#
b00000000000000000000000000100000 '
#17
0#
#18
1#
b00000000000000000000000000100100 '
#19
0#
#20
1#
b00000000000000000000000000101000 '
#21
0#
#22
1#
b00000000000000000000000000101100 '
#23
0#
#24
1#
b00000000000000000000000000110000 '
#25
0#
#26
1#
b00000000000000000000000000110100 '
#27
0#
#28
1#
b00000000000000000000000000111000 '
#29
0#
#30
1#
b00000000000000000000000000111100 '
#31
0#
#32
1#
b00000000000000000000000001000000 '
#33
0#
#34
1#
b00000000000000000000000001000100 '
#35
0#
#36
1#
b00000000000000000000000001001000 '
#37
0#
#38
1#
b00000000000000000000000001001100 '
#39
0#
#40
1#
b00000000000000000000000001010000 '
#41
0#
#42
1#
b00000000000000000000000001010100 '
#43
0#
#44
1#
b00000000000000000000000001011000 '
#45
0#
#46
1#
b00000000000000000000000001011100 '
#47
0#
#48
1#
b00000000000000000000000001100000 '
#49
0#
#50
1#
b00000000000000000000000001100100 '
#51
0#
#52
1#
b00000000000000000000000001101000 '
#53
0#
#54
1#
b00000000000000000000000001101100 '
#55
0#
#56
1#
b00000000000000000000000001110000 '
#57
0#
#58
1#
b00000000000000000000000001110100 '
#59
0#
#60
1#
b00000000000000000000000001111000 '
#61
0#
#62
1#
b00000000000000000000000001111100 '
#63
0#
#64
1#
b00000000000000000000000010000000 '
#65
0#
#66
1#
b00000000000000000000000010000100 '
#67
0#
#68
1#
b00000000000000000000000010001000 '
#69
0#
#70
1#
b00000000000000000000000010001100 '
#71
0#
#72
1#
b00000000000000000000000010010000 '
#73
0#
#74
1#
b00000000000000000000000010010100 '
#75
0#
#76
1#
b00000000000000000000000010011000 '
#77
0#
#78
1#
b00000000000000000000000010011100 '
#79
0#
#80
1#
b00000000000000000000000010100000 '
#81
0#
#82
1#
b00000000000000000000000010100100 '
#83
0#
#84
1#
b00000000000000000000000010101000 '
#85
0#
#86
1#
b00000000000000000000000010101100 '
#87
0#
#88
1#
b00000000000000000000000010110000 '
#89
0#
#90
1#
b00000000000000000000000010110100 '
#91
0#
#92
1#
b00000000000000000000000010111000 '
#93
0#
#94
1#
b00000000000000000000000010111100 '
#95
0#
#96
1#
b00000000000000000000000011000000 '
#97
0#
#98
1#
b00000000000000000000000011000100 '
#99
0#
#100
1#
b00000000000000000000000011001000 '
#101
0#
#102
1#
b00000000000000000000000011001100 '
#103
0#
#104
1#
b00000000000000000000000011010000 '
#105
0#
#106
1#
b00000000000000000000000011010100 '
#107
0#
#108
1#
b00000000000000000000000011011000 '
#109
0#
#110
1#
b00000000000000000000000011011100 '
#111
0#
#112
1#
b00000000000000000000000011100000 '
#113
0#
#114
1#
b00000000000000000000000011100100 '
#115
0#
#116
1#
b00000000000000000000000011101000 '
#117
0#
#118
1#
b00000000000000000000000011101100 '
#119
0#
#120
1#
b00000000000000000000000011110000 '
#121
0#
#122
1#
b00000000000000000000000011110100 '
#123
0#
#124
1#
b00000000000000000000000011111000 '
#125
0#
#126
1#
b00000000000000000000000011111100 '
#127
0#
#128
1#
b00000000000000000000000100000000 '
#129
0#
#130
1#
b00000000000000000000000100000100 '
#131
0#
#132
1#
b00000000000000000000000100001000 '
#133
0#
#134
1#
b00000000000000000000000100001100 '
#135
0#
#136
1#
b00000000000000000000000100010000 '
#137
0#
#138
1#
b00000000000000000000000100010100 '
#139
0#
#140
1#
b00000000000000000000000100011000 '
#141
0#
#142
1#
b00000000000000000000000100011100 '
#143
0#
#144
1#
b00000000000000000000000100100000 '
#145
0#
#146
1#
b00000000000000000000000100100100 '
#147
0#
#148
1#
b00000000000000000000000100101000 '
#149
0#
#150
1#
b00000000000000000000000100101100 '
#151
0#
#152
1#
b00000000000000000000000100110000 '
#153
0#
#154
1#
b00000000000000000000000100110100 '
#155
0#
#156
1#
b00000000000000000000000100111000 '
#157
0#
#158
1#
b00000000000000000000000100111100 '
#159
0#
#160
1#
b00000000000000000000000101000000 '
#161
0#
#162
1#
b00000000000000000000000101000100 '
#163
0#
#164
1#
b00000000000000000000000101001000 '
#165
0#
#166
1#
b00000000000000000000000101001100 '
#167
0#
#168
1#
b00000000000000000000000101010000 '
#169
0#
#170
1#
b00000000000000000000000101010100 '
#171
0#
#172
1#
b00000000000000000000000101011000 '
#173
0#
#174
1#
b00000000000000000000000101011100 '
#175
0#
#176
1#
b00000000000000000000000101100000 '
#177
0#
#178
1#
b00000000000000000000000101100100 '
#179
0#
#180
1#
b00000000000000000000000101101000 '
#181
0#
#182
1#
b00000000000000000000000101101100 '
#183
0#
#184
1#
b00000000000000000000000101110000 '
#185
0#
#186
1#
b00000000000000000000000101110100 '
#187
0#
#188
1#
b00000000000000000000000101111000 '
#189
0#
#190
1#
b00000000000000000000000101111100 '
#191
0#
#192
1#
b00000000000000000000000110000000 '
#193
0#
#194
1#
b00000000000000000000000110000100 '
#195
0#
#196
1#
b00000000000000000000000110001000 '
#197
0#
#198
1#
b00000000000000000000000110001100 '
#199
0#
#200
1#
b00000000000000000000000110010000 '
#201
0#
#202
1#
b00000000000000000000000110010100 '
#203
0#
#204
1#
b00000000000000000000000110011000 '
#205
0#
#206
1#
b00000000000000000000000110011100 '
#207
0#
#208
1#
b00000000000000000000000110100000 '
#209
0#
#210
1#
b00000000000000000000000110100100 '
#211
0#
#212
1#
b00000000000000000000000110101000 '
#213
0#
#214
1#
b00000000000000000000000110101100 '
#215
0#
#216
1#
b00000000000000000000000110110000 '
#217
0#
#218
1#
b00000000000000000000000110110100 '
#219
0#
#220
1#
b00000000000000000000000110111000 '
#221
0#
#222
1#
b00000000000000000000000110111100 '
#223
0#
#224
1#
b00000000000000000000000111000000 '
#225
0#
#226
1#
b00000000000000000000000111000100 '
#227
0#
#228
1#
b00000000000000000000000111001000 '
#229
0#
#230
1#
b00000000000000000000000111001100 '
#231
0#
#232
1#
b00000000000000000000000111010000 '
#233
0#
#234
1#
b00000000000000000000000111010100 '
#235
0#
#236
1#
b00000000000000000000000111011000 '
#237
0#
#238
1#
b00000000000000000000000111011100 '
#239
0#
#240
1#
b00000000000000000000000111100000 '
#241
0#
#242
1#
b00000000000000000000000111100100 '
#243
0#
#244
1#
b00000000000000000000000111101000 '
#245
0#
#246
1#
b00000000000000000000000111101100 '
#247
0#
#248
1#
b00000000000000000000000111110000 '
#249
0#
#250
1#
b00000000000000000000000111110100 '
#251
0#
#252
1#
b00000000000000000000000111111000 '
#253
0#
#254
1#
b00000000000000000000000111111100 '
#255
0#
#256
1#
b00000000000000000000001000000000 '
#257
0#
#258
1#
b00000000000000000000001000000100 '
#259
0#
#260
1#
b00000000000000000000001000001000 '
#261
0#
#262
1#
b00000000000000000000001000001100 '
#263
0#
#264
1#
b00000000000000000000001000010000 '
#265
0#
#266
1#
b00000000000000000000001000010100 '
#267
0#
#268
1#
b00000000000000000000001000011000 '
#269
0#
#270
1#
b00000000000000000000001000011100 '
#271
0#
#272
1#
b00000000000000000000001000100000 '
#273
0#
#274
1#
b00000000000000000000001000100100 '
#275
0#
#276
1#
b00000000000000000000001000101000 '
#277
0#
#278
1#
b00000000000000000000001000101100 '
#279
0#
#280
1#
b00000000000000000000001000110000 '
#281
0#
#282
1#
b00000000000000000000001000110100 '
#283
0#
#284
1#
b00000000000000000000001000111000 '
#285
0#
#286
1#
b00000000000000000000001000111100 '
#287
0#
#288
1#
b00000000000000000000001001000000 '
#289
0#
#290
1#
b00000000000000000000001001000100 '
#291
0#
#292
1#
b00000000000000000000001001001000 '
#293
0#
#294
1#
b00000000000000000000001001001100 '
#295
0#
#296
1#
b00000000000000000000001001010000 '
#297
0#
#298
1#
b00000000000000000000001001010100 '
#299
0#
#300
1#
b00000000000000000000001001011000 '
#301
0#
#302
1#
b00000000000000000000001001011100 '
#303
0#
#304
1#
b00000000000000000000001001100000 '
#305
0#
#306
1#
b00000000000000000000001001100100 '
#307
0#
#308
1#
b00000000000000000000001001101000 '
#309
0#
#310
1#
b00000000000000000000001001101100 '
#311
0#
#312
1#
b00000000000000000000001001110000 '
#313
0#
#314
1#
b00000000000000000000001001110100 '
#315
0#
#316
1#
b00000000000000000000001001111000 '
#317
0#
#318
1#
b00000000000000000000001001111100 '
#319
0#
#320
1#
b00000000000000000000001010000000 '
#321
0#
#322
1#
b00000000000000000000001010000100 '
#323
0#
#324
1#
b00000000000000000000001010001000 '
#325
0#
#326
1#
b00000000000000000000001010001100 '
#327
0#
#328
1#
b00000000000000000000001010010000 '
#329
0#
#330
1#
b00000000000000000000001010010100 '
#331
0#
#332
1#
b00000000000000000000001010011000 '
#333
0#
#334
1#
b00000000000000000000001010011100 '
#335
0#
#336
1#
b00000000000000000000001010100000 '
#337
0#
#338
1#
b00000000000000000000001010100100 '
#339
0#
#340
1#
b00000000000000000000001010101000 '
#341
0#
#342
1#
b00000000000000000000001010101100 '
#343
0#
#344
1#
b00000000000000000000001010110000 '
#345
0#
#346
1#
b00000000000000000000001010110100 '
#347
0#
#348
1#
b00000000000000000000001010111000 '
#349
0#
#350
1#
b00000000000000000000001010111100 '
#351
0#
#352
1#
b00000000000000000000001011000000 '
#353
0#
#354
1#
b00000000000000000000001011000100 '
#355
0#
#356
1#
b00000000000000000000001011001000 '
#357
0#
#358
1#
b00000000000000000000001011001100 '
#359
0#
#360
1#
b00000000000000000000001011010000 '
#361
0#
#362
1#
b00000000000000000000001011010100 '
#363
0#
#364
1#
b00000000000000000000001011011000 '
#365
0#
#366
1#
b00000000000000000000001011011100 '
#367
0#
#368
1#
b00000000000000000000001011100000 '
#369
0#
#370
1#
b00000000000000000000001011100100 '
#371
0#
#372
1#
b00000000000000000000001011101000 '
#373
0#
#374
1#
b00000000000000000000001011101100 '
#375
0#
#376
1#
b00000000000000000000001011110000 '
#377
0#
#378
1#
b00000000000000000000001011110100 '
#379
0#
#380
1#
b00000000000000000000001011111000 '
#381
0#
#382
1#
b00000000000000000000001011111100 '
#383
0#
#384
1#
b00000000000000000000001100000000 '
#385
0#
#386
1#
b00000000000000000000001100000100 '
#387
0#
#388
1#
b00000000000000000000001100001000 '
#389
0#
#390
1#
b00000000000000000000001100001100 '
#391
0#
#392
1#
b00000000000000000000001100010000 '
#393
0#
#394
1#
b00000000000000000000001100010100 '
#395
0#
#396
1#
b00000000000000000000001100011000 '
#397
0#
#398
1#
b00000000000000000000001100011100 '
#399
0#
#400
1#
b00000000000000000000001100100000 '
#401
0#
#402
1#
b00000000000000000000001100100100 '
#403
0#
#404
1#
b00000000000000000000001100101000 '
#405
0#
#406
1#
b00000000000000000000001100101100 '
#407
0#
#408
1#
b00000000000000000000001100110000 '
#409
0#
#410
1#
b00000000000000000000001100110100 '
#411
0#
#412
1#
b00000000000000000000001100111000 '
#413
0#
#414
1#
b00000000000000000000001100111100 '
#415
0#
#416
1#
b00000000000000000000001101000000 '
#417
0#
#418
1#
b00000000000000000000001101000100 '
#419
0#
#420
1#
b00000000000000000000001101001000 '
#421
0#
#422
1#
b00000000000000000000001101001100 '
#423
0#
#424
1#
b00000000000000000000001101010000 '
#425
0#
#426
1#
b00000000000000000000001101010100 '
#427
0#
#428
1#
b00000000000000000000001101011000 '
#429
0#
#430
1#
b00000000000000000000001101011100 '
#431
0#
#432
1#
b00000000000000000000001101100000 '
#433
0#
#434
1#
b00000000000000000000001101100100 '
#435
0#
#436
1#
b00000000000000000000001101101000 '
#437
0#
#438
1#
b00000000000000000000001101101100 '
#439
0#
#440
1#
b00000000000000000000001101110000 '
#441
0#
#442
1#
b00000000000000000000001101110100 '
#443
0#
#444
1#
b00000000000000000000001101111000 '
#445
0#
#446
1#
b00000000000000000000001101111100 '
#447
0#
#448
1#
b00000000000000000000001110000000 '
#449
0#
#450
1#
b00000000000000000000001110000100 '
#451
0#
#452
1#
b00000000000000000000001110001000 '
#453
0#
#454
1#
b00000000000000000000001110001100 '
#455
0#
#456
1#
b00000000000000000000001110010000 '
#457
0#
#458
1#
b00000000000000000000001110010100 '
#459
0#
#460
1#
b00000000000000000000001110011000 '
#461
0#
#462
1#
b00000000000000000000001110011100 '
#463
0#
#464
1#
b00000000000000000000001110100000 '
#465
0#
#466
1#
b00000000000000000000001110100100 '
#467
0#
#468
1#
b00000000000000000000001110101000 '
#469
0#
#470
1#
b00000000000000000000001110101100 '
#471
0#
#472
1#
b00000000000000000000001110110000 '
#473
0#
#474
1#
b00000000000000000000001110110100 '
#475
0#
#476
1#
b00000000000000000000001110111000 '
#477
0#
#478
1#
b00000000000000000000001110111100 '
#479
0#
#480
1#
b00000000000000000000001111000000 '
#481
0#
#482
1#
b00000000000000000000001111000100 '
#483
0#
#484
1#
b00000000000000000000001111001000 '
#485
0#
#486
1#
b00000000000000000000001111001100 '
#487
0#
#488
1#
b00000000000000000000001111010000 '
#489
0#
#490
1#
b00000000000000000000001111010100 '
#491
0#
#492
1#
b00000000000000000000001111011000 '
#493
0#
#494
1#
b00000000000000000000001111011100 '
#495
0#
#496
1#
b00000000000000000000001111100000 '
#497
0#
#498
1#
b00000000000000000000001111100100 '
#499
0#
#500
1#
b00000000000000000000001111101000 '
#501
0#
#502
1#
b00000000000000000000001111101100 '
#503
0#
#504
1#
b00000000000000000000001111110000 '
#505
0#
#506
1#
b00000000000000000000001111110100 '
#507
0#
#508
1#
b00000000000000000000001111111000 '
#509
0#
#510
1#
b00000000000000000000001111111100 '
#511
0#
#512
1#
b00000000000000000000010000000000 '
#513
0#
#514
1#
b00000000000000000000010000000100 '
#515
0#
#516
1#
b00000000000000000000010000001000 '
#517
0#
#518
1#
b00000000000000000000010000001100 '
#519
0#
#520
1#
b00000000000000000000010000010000 '
#521
0#
#522
1#
b00000000000000000000010000010100 '
#523
0#
#524
1#
b00000000000000000000010000011000 '
#525
0#
#526
1#
b00000000000000000000010000011100 '
#527
0#
#528
1#
b00000000000000000000010000100000 '
#529
0#
#530
1#
b00000000000000000000010000100100 '
#531
0#
#532
1#
b00000000000000000000010000101000 '
#533
0#
#534
1#
b00000000000000000000010000101100 '
#535
0#
#536
1#
b00000000000000000000010000110000 '
#537
0#
#538
1#
b00000000000000000000010000110100 '
#539
0#
#540
1#
b00000000000000000000010000111000 '
#541
0#
#542
1#
b00000000000000000000010000111100 '
#543
0#
#544
1#
b00000000000000000000010001000000 '
#545
0#
#546
1#
b00000000000000000000010001000100 '
#547
0#
#548
1#
b00000000000000000000010001001000 '
#549
0#
#550
1#
b00000000000000000000010001001100 '
#551
0#
#552
1#
b00000000000000000000010001010000 '
#553
0#
#554
1#
b00000000000000000000010001010100 '
#555
0#
#556
1#
b00000000000000000000010001011000 '
#557
0#
#558
1#
b00000000000000000000010001011100 '
#559
0#
#560
1#
b00000000000000000000010001100000 '
#561
0#
#562
1#
b00000000000000000000010001100100 '
#563
0#
#564
1#
b00000000000000000000010001101000 '
#565
0#
#566
1#
b00000000000000000000010001101100 '
#567
0#
#568
1#
b00000000000000000000010001110000 '
#569
0#
#570
1#
b00000000000000000000010001110100 '
#571
0#
#572
1#
b00000000000000000000010001111000 '
#573
0#
#574
1#
b00000000000000000000010001111100 '
#575
0#
#576
1#
b00000000000000000000010010000000 '
#577
0#
#578
1#
b00000000000000000000010010000100 '
#579
0#
#580
1#
b00000000000000000000010010001000 '
#581
0#
#582
1#
b00000000000000000000010010001100 '
#583
0#
#584
1#
b00000000000000000000010010010000 '
#585
0#
#586
1#
b00000000000000000000010010010100 '
#587
0#
#588
1#
b00000000000000000000010010011000 '
#589
0#
#590
1#
b00000000000000000000010010011100 '
#591
0#
#592
1#
b00000000000000000000010010100000 '
#593
0#
#594
1#
b00000000000000000000010010100100 '
#595
0#
#596
1#
b00000000000000000000010010101000 '
#597
0#
#598
1#
b00000000000000000000010010101100 '
#599
0#
#600
1#
b00000000000000000000010010110000 '
#601
0#
#602
1#
b00000000000000000000010010110100 '
#603
0#
#604
1#
b00000000000000000000010010111000 '
#605
0#
#606
1#
b00000000000000000000010010111100 '
#607
0#
#608
1#
b00000000000000000000010011000000 '
#609
0#
#610
1#
b00000000000000000000010011000100 '
#611
0#
#612
1#
b00000000000000000000010011001000 '
#613
0#
#614
1#
b00000000000000000000010011001100 '
#615
0#
#616
1#
b00000000000000000000010011010000 '
#617
0#
#618
1#
b00000000000000000000010011010100 '
#619
0#
#620
1#
b00000000000000000000010011011000 '
#621
0#
#622
1#
b00000000000000000000010011011100 '
#623
0#
#624
1#
b00000000000000000000010011100000 '
#625
0#
#626
1#
b00000000000000000000010011100100 '
#627
0#
#628
1#
b00000000000000000000010011101000 '
#629
0#
#630
1#
b00000000000000000000010011101100 '
#631
0#
#632
1#
b00000000000000000000010011110000 '
#633
0#
#634
1#
b00000000000000000000010011110100 '
#635
0#
#636
1#
b00000000000000000000010011111000 '
#637
0#
#638
1#
b00000000000000000000010011111100 '
#639
0#
#640
1#
b00000000000000000000010100000000 '
#641
0#
#642
1#
b00000000000000000000010100000100 '
#643
0#
#644
1#
b00000000000000000000010100001000 '
#645
0#
#646
1#
b00000000000000000000010100001100 '
#647
0#
#648
1#
b00000000000000000000010100010000 '
#649
0#
#650
1#
b00000000000000000000010100010100 '
#651
0#
#652
1#
b00000000000000000000010100011000 '
#653
0#
#654
1#
b00000000000000000000010100011100 '
#655
0#
#656
1#
b00000000000000000000010100100000 '
#657
0#
#658
1#
b00000000000000000000010100100100 '
#659
0#
#660
1#
b00000000000000000000010100101000 '
#661
0#
#662
1#
b00000000000000000000010100101100 '
#663
0#
#664
1#
b00000000000000000000010100110000 '
#665
0#
#666
1#
b00000000000000000000010100110100 '
#667
0#
#668
1#
b00000000000000000000010100111000 '
#669
0#
#670
1#
b00000000000000000000010100111100 '
#671
0#
#672
1#
b00000000000000000000010101000000 '
#673
0#
#674
1#
b00000000000000000000010101000100 '
#675
0#
#676
1#
b00000000000000000000010101001000 '
#677
0#
#678
1#
b00000000000000000000010101001100 '
#679
0#
#680
1#
b00000000000000000000010101010000 '
#681
0#
#682
1#
b00000000000000000000010101010100 '
#683
0#
#684
1#
b00000000000000000000010101011000 '
#685
0#
#686
1#
b00000000000000000000010101011100 '
#687
0#
#688
1#
b00000000000000000000010101100000 '
#689
0#
#690
1#
b00000000000000000000010101100100 '
#691
0#
#692
1#
b00000000000000000000010101101000 '
#693
0#
#694
1#
b00000000000000000000010101101100 '
#695
0#
#696
1#
b00000000000000000000010101110000 '
#697
0#
#698
1#
b00000000000000000000010101110100 '
#699
0#
#700
1#
b00000000000000000000010101111000 '
#701
0#
#702
1#
b00000000000000000000010101111100 '
#703
0#
#704
1#
b00000000000000000000010110000000 '
#705
0#
#706
1#
b00000000000000000000010110000100 '
#707
0#
#708
1#
b00000000000000000000010110001000 '
#709
0#
#710
1#
b00000000000000000000010110001100 '
#711
0#
#712
1#
b00000000000000000000010110010000 '
#713
0#
#714
1#
b00000000000000000000010110010100 '
#715
0#
#716
1#
b00000000000000000000010110011000 '
#717
0#
#718
1#
b00000000000000000000010110011100 '
#719
0#
#720
1#
b00000000000000000000010110100000 '
#721
0#
#722
1#
b00000000000000000000010110100100 '
#723
0#
#724
1#
b00000000000000000000010110101000 '
#725
0#
#726
1#
b00000000000000000000010110101100 '
#727
0#
#728
1#
b00000000000000000000010110110000 '
#729
0#
#730
1#
b00000000000000000000010110110100 '
#731
0#
#732
1#
b00000000000000000000010110111000 '
#733
0#
#734
1#
b00000000000000000000010110111100 '
#735
0#
#736
1#
b00000000000000000000010111000000 '
#737
0#
#738
1#
b00000000000000000000010111000100 '
#739
0#
#740
1#
b00000000000000000000010111001000 '
#741
0#
#742
1#
b00000000000000000000010111001100 '
#743
0#
#744
1#
b00000000000000000000010111010000 '
#745
0#
#746
1#
b00000000000000000000010111010100 '
#747
0#
#748
1#
b00000000000000000000010111011000 '
#749
0#
#750
1#
b00000000000000000000010111011100 '
#751
0#
#752
1#
b00000000000000000000010111100000 '
#753
0#
#754
1#
b00000000000000000000010111100100 '
#755
0#
#756
1#
b00000000000000000000010111101000 '
#757
0#
#758
1#
b00000000000000000000010111101100 '
#759
0#
#760
1#
b00000000000000000000010111110000 '
#761
0#
#762
1#
b00000000000000000000010111110100 '
#763
0#
#764
1#
b00000000000000000000010111111000 '
#765
0#
#766
1#
b00000000000000000000010111111100 '
#767
0#
#768
1#
b00000000000000000000011000000000 '
#769
0#
#770
1#
b00000000000000000000011000000100 '
#771
0#
#772
1#
b00000000000000000000011000001000 '
#773
0#
#774
1#
b00000000000000000000011000001100 '
#775
0#
#776
1#
b00000000000000000000011000010000 '
#777
0#
#778
1#
b00000000000000000000011000010100 '
#779
0#
#780
1#
b00000000000000000000011000011000 '
#781
0#
#782
1#
b00000000000000000000011000011100 '
#783
0#
#784
1#
b00000000000000000000011000100000 '
#785
0#
#786
1#
b00000000000000000000011000100100 '
#787
0#
#788
1#
b00000000000000000000011000101000 '
#789
0#
#790
1#
b00000000000000000000011000101100 '
#791
0#
#792
1#
b00000000000000000000011000110000 '
#793
0#
#794
1#
b00000000000000000000011000110100 '
#795
0#
#796
1#
b00000000000000000000011000111000 '
#797
0#
#798
1#
b00000000000000000000011000111100 '
#799
0#
#800
1#
b00000000000000000000011001000000 '
#801
0#
#802
1#
b00000000000000000000011001000100 '
#803
0#
#804
1#
b00000000000000000000011001001000 '
#805
0#
#806
1#
b00000000000000000000011001001100 '
#807
0#
#808
1#
b00000000000000000000011001010000 '
#809
0#
#810
1#
b00000000000000000000011001010100 '
#811
0#
#812
1#
b00000000000000000000011001011000 '
#813
0#
#814
1#
b00000000000000000000011001011100 '
#815
0#
#816
1#
b00000000000000000000011001100000 '
#817
0#
#818
1#
b00000000000000000000011001100100 '
#819
0#
#820
1#
b00000000000000000000011001101000 '
#821
0#
#822
1#
b00000000000000000000011001101100 '
#823
0#
#824
1#
b00000000000000000000011001110000 '
#825
0#
#826
1#
b00000000000000000000011001110100 '
#827
0#
#828
1#
b00000000000000000000011001111000 '
#829
0#
#830
1#
b00000000000000000000011001111100 '
#831
0#
#832
1#
b00000000000000000000011010000000 '
#833
0#
#834
1#
b00000000000000000000011010000100 '
#835
0#
#836
1#
b00000000000000000000011010001000 '
#837
0#
#838
1#
b00000000000000000000011010001100 '
#839
0#
#840
1#
b00000000000000000000011010010000 '
#841
0#
#842
1#
b00000000000000000000011010010100 '
#843
0#
#844
1#
b00000000000000000000011010011000 '
#845
0#
#846
1#
b00000000000000000000011010011100 '
#847
0#
#848
1#
b00000000000000000000011010100000 '
#849
0#
#850
1#
b00000000000000000000011010100100 '
#851
0#
#852
1#
b00000000000000000000011010101000 '
#853
0#
#854
1#
b00000000000000000000011010101100 '
#855
0#
#856
1#
b00000000000000000000011010110000 '
#857
0#
#858
1#
b00000000000000000000011010110100 '
#859
0#
#860
1#
b00000000000000000000011010111000 '
#861
0#
#862
1#
b00000000000000000000011010111100 '
#863
0#
#864
1#
b00000000000000000000011011000000 '
#865
0#
#866
1#
b00000000000000000000011011000100 '
#867
0#
#868
1#
b00000000000000000000011011001000 '
#869
0#
#870
1#
b00000000000000000000011011001100 '
#871
0#
#872
1#
b00000000000000000000011011010000 '
#873
0#
#874
1#
b00000000000000000000011011010100 '
#875
0#
#876
1#
b00000000000000000000011011011000 '
#877
0#
#878
1#
b00000000000000000000011011011100 '
#879
0#
#880
1#
b00000000000000000000011011100000 '
#881
0#
#882
1#
b00000000000000000000011011100100 '
#883
0#
#884
1#
b00000000000000000000011011101000 '
#885
0#
#886
1#
b00000000000000000000011011101100 '
#887
0#
#888
1#
b00000000000000000000011011110000 '
#889
0#
#890
1#
b00000000000000000000011011110100 '
#891
0#
#892
1#
b00000000000000000000011011111000 '
#893
0#
#894
1#
b00000000000000000000011011111100 '
#895
0#
#896
1#
b00000000000000000000011100000000 '
#897
0#
#898
1#
b00000000000000000000011100000100 '
#899
0#
#900
1#
b00000000000000000000011100001000 '
#901
0#
#902
1#
b00000000000000000000011100001100 '
#903
0#
#904
1#
b00000000000000000000011100010000 '
#905
0#
#906
1#
b00000000000000000000011100010100 '
#907
0#
#908
1#
b00000000000000000000011100011000 '
#909
0#
#910
1#
b00000000000000000000011100011100 '
#911
0#
#912
1#
b00000000000000000000011100100000 '
#913
0#
#914
1#
b00000000000000000000011100100100 '
#915
0#
#916
1#
b00000000000000000000011100101000 '
#917
0#
#918
1#
b00000000000000000000011100101100 '
#919
0#
#920
1#
b00000000000000000000011100110000 '
#921
0#
#922
1#
b00000000000000000000011100110100 '
#923
0#
#924
1#
b00000000000000000000011100111000 '
#925
0#
#926
1#
b00000000000000000000011100111100 '
#927
0#
#928
1#
b00000000000000000000011101000000 '
#929
0#
#930
1#
b00000000000000000000011101000100 '
#931
0#
#932
1#
b00000000000000000000011101001000 '
#933
0#
#934
1#
b00000000000000000000011101001100 '
#935
0#
#936
1#
b00000000000000000000011101010000 '
#937
0#
#938
1#
b00000000000000000000011101010100 '
#939
0#
#940
1#
b00000000000000000000011101011000 '
#941
0#
#942
1#
b00000000000000000000011101011100 '
#943
0#
#944
1#
b00000000000000000000011101100000 '
#945
0#
#946
1#
b00000000000000000000011101100100 '
#947
0#
#948
1#
b00000000000000000000011101101000 '
#949
0#
#950
1#
b00000000000000000000011101101100 '
#951
0#
#952
1#
b00000000000000000000011101110000 '
#953
0#
#954
1#
b00000000000000000000011101110100 '
#955
0#
#956
1#
b00000000000000000000011101111000 '
#957
0#
#958
1#
b00000000000000000000011101111100 '
#959
0#
#960
1#
b00000000000000000000011110000000 '
#961
0#
#962
1#
b00000000000000000000011110000100 '
#963
0#
#964
1#
b00000000000000000000011110001000 '
#965
0#
#966
1#
b00000000000000000000011110001100 '
#967
0#
#968
1#
b00000000000000000000011110010000 '
#969
0#
#970
1#
b00000000000000000000011110010100 '
#971
0#
#972
1#
b00000000000000000000011110011000 '
#973
0#
#974
1#
b00000000000000000000011110011100 '
#975
0#
#976
1#
b00000000000000000000011110100000 '
#977
0#
#978
1#
b00000000000000000000011110100100 '
#979
0#
#980
1#
b00000000000000000000011110101000 '
#981
0#
#982
1#
b00000000000000000000011110101100 '
#983
0#
#984
1#
b00000000000000000000011110110000 '
#985
0#
#986
1#
b00000000000000000000011110110100 '
#987
0#
#988
1#
b00000000000000000000011110111000 '
#989
0#
#990
1#
b00000000000000000000011110111100 '
#991
0#
#992
1#
b00000000000000000000011111000000 '
#993
0#
#994
1#
b00000000000000000000011111000100 '
#995
0#
#996
1#
b00000000000000000000011111001000 '
#997
0#
#998
1#
b00000000000000000000011111001100 '
#999
0#
#1000
1#
b00000000000000000000011111010000 '
#1001
0#
#1002
1#
b00000000000000000000011111010100 '
#1003
0#
#1004
1#
b00000000000000000000011111011000 '
#1005
0#
#1006
1#
b00000000000000000000011111011100 '
#1007
0#
#1008
1#
b00000000000000000000011111100000 '
#1009
0#
#1010
1#
b00000000000000000000011111100100 '
#1011
0#
#1012
1#
b00000000000000000000011111101000 '
#1013
0#
#1014
1#
b00000000000000000000011111101100 '
#1015
0#
#1016
1#
b00000000000000000000011111110000 '
#1017
0#
#1018
1#
b00000000000000000000011111110100 '
#1019
0#
#1020
1#
b00000000000000000000011111111000 '
#1021
0#
#1022
1#
b00000000000000000000011111111100 '
#1023
0#
#1024
1#
b00000000000000000000100000000000 '
#1025
0#
#1026
1#
b00000000000000000000100000000100 '
#1027
0#
